Weather/Core.py
Weather/__init__.py
erispulse_weather-1.1.0.dist-info/entry_points.txt
erispulse_weather-1.1.0.dist-info/licenses/LICENSE
erispulse_weather-1.1.0.dist-info/WHEEL
erispulse_weather-1.1.0.dist-info/METADATA
erispulse_weather-1.1.0.dist-info/RECORD
