Metadata-Version: 2.4
Name: ErisPulse-Weather
Version: 1.1.0
Summary: 天气查询，支持绑定城市、今日天气、五日天气
Author-email: ShanFish <zcsfish@qq.com>
Requires-Python: >=3.9
License-File: LICENSE
Requires-Dist: aiohttp
Project-URL: homepage, https://github.com/shanfishapp/ErisPulse-Weather
